token1/__init__.py
token1-0.0.1.dist-info/METADATA
token1-0.0.1.dist-info/WHEEL
token1-0.0.1.dist-info/licenses/LICENSE
token1-0.0.1.dist-info/RECORD
